time_series_cross_validation
